{
  "id": "oval:org.opensuse.security:ste:2009185758",
  "attr_version": "1",
  "xmlns": "http://oval.mitre.org/XMLSchema/oval-definitions-5#linux",
  "version": {},
  "evr": {
    "text": "0:0.5.0-3.5.1",
    "datatype": "evr_string",
    "operation": "less than"
  },
  "signature_keyid": {},
  "arch": {
    "text": "(libwebp-devel|libwebp-devel-32bit|libwebp-devel-64bit|libwebp-tools|libwebp6|libwebp6-32bit|libwebp6-64bit|libwebpdecoder2|libwebpdecoder2-32bit|libwebpdecoder2-64bit|libwebpdemux2|libwebpdemux2-32bit|libwebpdemux2-64bit|libwebpextras0|libwebpextras0-32bit|libwebpextras0-64bit|libwebpmux2|libwebpmux2-32bit|libwebpmux2-64bit)",
    "datatype": "string",
    "operation": "pattern match"
  }
}
